src/letters-font/__init__.py
src/letters-font/main.py
letters_font-0.0.1.dist-info/METADATA
letters_font-0.0.1.dist-info/WHEEL
letters_font-0.0.1.dist-info/licenses/LICENSE
letters_font-0.0.1.dist-info/RECORD
